sgp30/__init__.py
sgp30/_version.py
sgp30/humidity.py
sgp30/py.typed
sgp30/sgp30.py
sgp30_driver-0.2.2.dist-info/LICENSE
sgp30_driver-0.2.2.dist-info/METADATA
sgp30_driver-0.2.2.dist-info/WHEEL
sgp30_driver-0.2.2.dist-info/top_level.txt
sgp30_driver-0.2.2.dist-info/RECORD
