Metadata-Version: 2.1
Name: sgp30-driver
Version: 0.2.2
Summary: Python driver for the Sensirion SGP30 multi gas sensor
Author-email: Rogier van der Geer <rogier@vander-geer.nl>
Project-URL: Repository, https://github.com/rogiervandergeer/sgp30-driver
Classifier: Programming Language :: Python :: 3
Classifier: License :: OSI Approved :: Apache Software License
Classifier: Topic :: System :: Hardware :: Hardware Drivers
Classifier: Typing :: Typed
License-File: LICENSE
Requires-Dist: smbus2 >=0.3.0
Provides-Extra: dev
Requires-Dist: pytest ; extra == 'dev'
Requires-Dist: pytest-mock ; extra == 'dev'
